
{
  "personal_website": "ุงููููุน ุงูุดุฎุตู ููููุฏู ุนุจุฏ ุงููู",
  "about_me": "ูุจุฐุฉ ุนูู",
  "about_me_description": "๐ ูุฑุญุจูุง! ุฃูุง ุงูููุฏู ุนุจุฏ ุงูููุ ูุทูุฑ ููุจ ูุญุชุฑู ูุชุฎุตุต ูู PHP ูุชูููุงุช ุงูููุจ ุงููุชูุฏูุฉ. ุฃุณุนู ูุชุทููุฑ ุญููู ูุนูุงูุฉ ูุฅุจุฑุงุฒ ูุดุงุฑูุนู ุจุทุฑููุฉ ูุจุชูุฑุฉ.",
  "projects": "๐ ุงููุดุงุฑูุน",
  "currently_learning": "๐ฑ ูุฌุงูุงุช ุงูุชุนูู ุงูุญุงููุฉ",
  "currently_learning_items": [
    "ุฃุทุฑ ุนูู PHP ุงููุชูุฏูุฉ ูุฃููุงุท ุงูุชุตููู",
    "ุชุญุณูู ุงูุชูุงูู ูุน ุงูุณุญุงุจุฉ ูุชุทุจููุงุช ุงูููุจ"
  ],
  "contact_me": "๐ซ ููููุฉ ุงูุชูุงุตู ูุนู",
  "email": "ุงูุจุฑูุฏ ุงูุฅููุชุฑููู",
  "previous": "ุงูุณุงุจู",
  "next": "ุงูุชุงูู"
}